[
  {
    "id": 1,
    "name": "Cart",
    "deploy_from_collectible_id": 128,
    "deploy_time": 5.0,
    "deployable_type": "Cart",
    "pathfinding_id": 1375685503,
    "movement_type": "Ground",
    "can_enter_portals": true,
    "speed": [
      {
        "surface_type": "Ground",
        "speed": 13.0
      },
      {
        "surface_type": "Lake",
        "speed": 0.0
      },
      {
        "surface_type": "River",
        "speed": 0.0
      },
      {
        "surface_type": "Ocean",
        "speed": 0.0
      },
      {
        "surface_type": "OceanBiome",
        "speed": 0.0
      },
      {
        "surface_type": "Swamp",
        "speed": 0.0
      }
    ],
    "use_player_speed_modifier": true,
    "placeable_on_land": true,
    "placeable_in_water": false,
    "capacity": 1,
    "storage": 12,
    "stockpile": 1,
    "barter": 0,
    "item_slot_size": 6000,
    "cargo_slot_size": 60000,
    "model_address": "Vehicles/Cart",
    "stats": [],
    "player_animations_in_deployable_slots": [
      1
    ],
    "allow_driver_extract": false,
    "allow_passenger_extract": false,
    "show_for_secs_after_owner_logout": 0,
    "allow_emote_while_driver": false,
    "allow_emote_while_passenger": false,
    "experience_per_progress": [],
    "mounting_radius": 3.0
  },
  {
    "id": 2,
    "name": "Wagon",
    "deploy_from_collectible_id": 129,
    "deploy_time": 5.0,
    "deployable_type": "Cart",
    "pathfinding_id": 1030168975,
    "movement_type": "Ground",
    "can_enter_portals": true,
    "speed": [
      {
        "surface_type": "Ground",
        "speed": 10.0
      },
      {
        "surface_type": "Lake",
        "speed": 0.0
      },
      {
        "surface_type": "River",
        "speed": 0.0
      },
      {
        "surface_type": "Ocean",
        "speed": 0.0
      },
      {
        "surface_type": "OceanBiome",
        "speed": 0.0
      },
      {
        "surface_type": "Swamp",
        "speed": 0.0
      }
    ],
    "use_player_speed_modifier": true,
    "placeable_on_land": true,
    "placeable_in_water": false,
    "capacity": 1,
    "storage": 12,
    "stockpile": 6,
    "barter": 0,
    "item_slot_size": 6000,
    "cargo_slot_size": 60000,
    "model_address": "Vehicles/LargeCart",
    "stats": [],
    "player_animations_in_deployable_slots": [
      1
    ],
    "allow_driver_extract": false,
    "allow_passenger_extract": false,
    "show_for_secs_after_owner_logout": 0,
    "allow_emote_while_driver": false,
    "allow_emote_while_passenger": false,
    "experience_per_progress": [],
    "mounting_radius": 3.0
  },
  {
    "id": 3,
    "name": "Raft",
    "deploy_from_collectible_id": 130,
    "deploy_time": 5.0,
    "deployable_type": "Boat",
    "pathfinding_id": 1109261591,
    "movement_type": "Water",
    "can_enter_portals": false,
    "speed": [
      {
        "surface_type": "Ground",
        "speed": 0.0
      },
      {
        "surface_type": "Lake",
        "speed": 14.0
      },
      {
        "surface_type": "River",
        "speed": 14.0
      },
      {
        "surface_type": "Ocean",
        "speed": 10.0
      },
      {
        "surface_type": "OceanBiome",
        "speed": 10.0
      },
      {
        "surface_type": "Swamp",
        "speed": 14.0
      }
    ],
    "use_player_speed_modifier": false,
    "placeable_on_land": false,
    "placeable_in_water": true,
    "capacity": 2,
    "storage": 6,
    "stockpile": 1,
    "barter": 0,
    "item_slot_size": 6000,
    "cargo_slot_size": 60000,
    "model_address": "Vehicles/BoatRaft",
    "stats": [],
    "player_animations_in_deployable_slots": [
      1002,
      1002
    ],
    "allow_driver_extract": true,
    "allow_passenger_extract": true,
    "show_for_secs_after_owner_logout": 0,
    "allow_emote_while_driver": false,
    "allow_emote_while_passenger": false,
    "experience_per_progress": [
      {
        "skill_id": 21,
        "quantity": 0.0
      }
    ],
    "mounting_radius": 3.0
  },
  {
    "id": 4,
    "name": "Skiff",
    "deploy_from_collectible_id": 131,
    "deploy_time": 5.0,
    "deployable_type": "Boat",
    "pathfinding_id": 865980458,
    "movement_type": "Water",
    "can_enter_portals": false,
    "speed": [
      {
        "surface_type": "Ground",
        "speed": 0.0
      },
      {
        "surface_type": "Lake",
        "speed": 21.0
      },
      {
        "surface_type": "River",
        "speed": 21.0
      },
      {
        "surface_type": "Ocean",
        "speed": 15.0
      },
      {
        "surface_type": "OceanBiome",
        "speed": 15.0
      },
      {
        "surface_type": "Swamp",
        "speed": 21.0
      }
    ],
    "use_player_speed_modifier": false,
    "placeable_on_land": false,
    "placeable_in_water": true,
    "capacity": 3,
    "storage": 24,
    "stockpile": 4,
    "barter": 0,
    "item_slot_size": 6000,
    "cargo_slot_size": 60000,
    "model_address": "Vehicles/Skiff",
    "stats": [],
    "player_animations_in_deployable_slots": [
      1002,
      1002
    ],
    "allow_driver_extract": true,
    "allow_passenger_extract": true,
    "show_for_secs_after_owner_logout": 0,
    "allow_emote_while_driver": true,
    "allow_emote_while_passenger": true,
    "experience_per_progress": [
      {
        "skill_id": 21,
        "quantity": 0.0
      }
    ],
    "mounting_radius": 5.0
  },
  {
    "id": 6,
    "name": "Rideable Deer",
    "deploy_from_collectible_id": 127,
    "deploy_time": 3.0,
    "deployable_type": "Mount",
    "pathfinding_id": 309954853,
    "movement_type": "Ground",
    "can_enter_portals": true,
    "speed": [
      {
        "surface_type": "Ground",
        "speed": 25.0
      },
      {
        "surface_type": "Lake",
        "speed": 0.0
      },
      {
        "surface_type": "River",
        "speed": 0.0
      },
      {
        "surface_type": "Ocean",
        "speed": 0.0
      },
      {
        "surface_type": "OceanBiome",
        "speed": 0.0
      },
      {
        "surface_type": "Swamp",
        "speed": 0.0
      }
    ],
    "use_player_speed_modifier": false,
    "placeable_on_land": true,
    "placeable_in_water": false,
    "capacity": 1,
    "storage": 0,
    "stockpile": 1,
    "barter": 0,
    "item_slot_size": 6000,
    "cargo_slot_size": 18000,
    "model_address": "Vehicles/DeerMount",
    "stats": [],
    "player_animations_in_deployable_slots": [
      2
    ],
    "allow_driver_extract": false,
    "allow_passenger_extract": false,
    "show_for_secs_after_owner_logout": 0,
    "allow_emote_while_driver": false,
    "allow_emote_while_passenger": false,
    "experience_per_progress": [
      {
        "skill_id": 17,
        "quantity": 0.0
      }
    ],
    "mounting_radius": 3.0
  },
  {
    "id": 7,
    "name": "Fisherman's Boat",
    "deploy_from_collectible_id": 132,
    "deploy_time": 5.0,
    "deployable_type": "Boat",
    "pathfinding_id": 1088877698,
    "movement_type": "Water",
    "can_enter_portals": false,
    "speed": [
      {
        "surface_type": "Ground",
        "speed": 0.0
      },
      {
        "surface_type": "Lake",
        "speed": 30.0
      },
      {
        "surface_type": "River",
        "speed": 30.0
      },
      {
        "surface_type": "Ocean",
        "speed": 30.0
      },
      {
        "surface_type": "OceanBiome",
        "speed": 30.0
      },
      {
        "surface_type": "Swamp",
        "speed": 30.0
      }
    ],
    "use_player_speed_modifier": false,
    "placeable_on_land": false,
    "placeable_in_water": true,
    "capacity": 4,
    "storage": 40,
    "stockpile": 6,
    "barter": 0,
    "item_slot_size": 6000,
    "cargo_slot_size": 180000,
    "model_address": "Vehicles/SmallVessel",
    "stats": [
      {
        "id": "CraftingSpeed",
        "value": 0.05,
        "is_pct": true
      }
    ],
    "player_animations_in_deployable_slots": [
      1002,
      1002
    ],
    "allow_driver_extract": true,
    "allow_passenger_extract": true,
    "show_for_secs_after_owner_logout": 0,
    "allow_emote_while_driver": false,
    "allow_emote_while_passenger": false,
    "experience_per_progress": [],
    "mounting_radius": 3.0
  },
  {
    "id": 8,
    "name": "Cheater's Boat",
    "deploy_from_collectible_id": 133,
    "deploy_time": 5.0,
    "deployable_type": "Boat",
    "pathfinding_id": 691415579,
    "movement_type": "Water",
    "can_enter_portals": false,
    "speed": [
      {
        "surface_type": "Ground",
        "speed": 0.0
      },
      {
        "surface_type": "Lake",
        "speed": 75.0
      },
      {
        "surface_type": "River",
        "speed": 75.0
      },
      {
        "surface_type": "Ocean",
        "speed": 75.0
      },
      {
        "surface_type": "OceanBiome",
        "speed": 75.0
      },
      {
        "surface_type": "Swamp",
        "speed": 75.0
      }
    ],
    "use_player_speed_modifier": false,
    "placeable_on_land": false,
    "placeable_in_water": true,
    "capacity": 2,
    "storage": 0,
    "stockpile": 0,
    "barter": 0,
    "item_slot_size": 6000,
    "cargo_slot_size": 6000,
    "model_address": "Vehicles/Canoe",
    "stats": [],
    "player_animations_in_deployable_slots": [
      1002,
      1002
    ],
    "allow_driver_extract": true,
    "allow_passenger_extract": true,
    "show_for_secs_after_owner_logout": 0,
    "allow_emote_while_driver": false,
    "allow_emote_while_passenger": false,
    "experience_per_progress": [],
    "mounting_radius": 5.0
  },
  {
    "id": 13,
    "name": "Trader Cart",
    "deploy_from_collectible_id": 138,
    "deploy_time": 3.0,
    "deployable_type": "Cart",
    "pathfinding_id": 516255236,
    "movement_type": "Ground",
    "can_enter_portals": true,
    "speed": [
      {
        "surface_type": "Ground",
        "speed": 13.0
      },
      {
        "surface_type": "Lake",
        "speed": 0.0
      },
      {
        "surface_type": "River",
        "speed": 0.0
      },
      {
        "surface_type": "Ocean",
        "speed": 0.0
      },
      {
        "surface_type": "OceanBiome",
        "speed": 0.0
      },
      {
        "surface_type": "Swamp",
        "speed": 0.0
      }
    ],
    "use_player_speed_modifier": true,
    "placeable_on_land": true,
    "placeable_in_water": false,
    "capacity": 1,
    "storage": 32,
    "stockpile": 20,
    "barter": 20,
    "item_slot_size": 6000,
    "cargo_slot_size": 120000,
    "model_address": "Vehicles/Cart",
    "stats": [],
    "player_animations_in_deployable_slots": [
      1
    ],
    "allow_driver_extract": false,
    "allow_passenger_extract": false,
    "show_for_secs_after_owner_logout": 86400,
    "allow_emote_while_driver": false,
    "allow_emote_while_passenger": false,
    "experience_per_progress": [],
    "mounting_radius": 3.0
  },
  {
    "id": 14,
    "name": "Trader Stand",
    "deploy_from_collectible_id": 139,
    "deploy_time": 3.0,
    "deployable_type": "Stall",
    "pathfinding_id": 1525146351,
    "movement_type": "None",
    "can_enter_portals": false,
    "speed": [
      {
        "surface_type": "Ground",
        "speed": 0.0
      },
      {
        "surface_type": "Lake",
        "speed": 0.0
      },
      {
        "surface_type": "River",
        "speed": 0.0
      },
      {
        "surface_type": "Ocean",
        "speed": 0.0
      },
      {
        "surface_type": "OceanBiome",
        "speed": 0.0
      },
      {
        "surface_type": "Swamp",
        "speed": 0.0
      }
    ],
    "use_player_speed_modifier": false,
    "placeable_on_land": true,
    "placeable_in_water": false,
    "capacity": 0,
    "storage": 10,
    "stockpile": 4,
    "barter": 10,
    "item_slot_size": 60000,
    "cargo_slot_size": 600000,
    "model_address": "Vehicles/TraderStand",
    "stats": [],
    "player_animations_in_deployable_slots": [],
    "allow_driver_extract": false,
    "allow_passenger_extract": false,
    "show_for_secs_after_owner_logout": 86400,
    "allow_emote_while_driver": false,
    "allow_emote_while_passenger": false,
    "experience_per_progress": [],
    "mounting_radius": 3.0
  },
  {
    "id": 1000,
    "name": "Siege Engine",
    "deploy_from_collectible_id": 0,
    "deploy_time": 0.0,
    "deployable_type": "SiegeEngine",
    "pathfinding_id": 1525146351,
    "movement_type": "None",
    "can_enter_portals": false,
    "speed": [
      {
        "surface_type": "Ground",
        "speed": 0.0
      },
      {
        "surface_type": "Lake",
        "speed": 0.0
      },
      {
        "surface_type": "River",
        "speed": 0.0
      },
      {
        "surface_type": "Ocean",
        "speed": 0.0
      },
      {
        "surface_type": "OceanBiome",
        "speed": 0.0
      },
      {
        "surface_type": "Swamp",
        "speed": 0.0
      }
    ],
    "use_player_speed_modifier": false,
    "placeable_on_land": true,
    "placeable_in_water": false,
    "capacity": 0,
    "storage": 0,
    "stockpile": 0,
    "barter": 0,
    "item_slot_size": 6000,
    "cargo_slot_size": 0,
    "model_address": "Vehicles/SiegeEngine",
    "stats": [],
    "player_animations_in_deployable_slots": [],
    "allow_driver_extract": false,
    "allow_passenger_extract": false,
    "show_for_secs_after_owner_logout": 0,
    "allow_emote_while_driver": false,
    "allow_emote_while_passenger": false,
    "experience_per_progress": [],
    "mounting_radius": 3.0
  },
  {
    "id": 228937650,
    "name": "Clipper",
    "deploy_from_collectible_id": 1142862651,
    "deploy_time": 5.0,
    "deployable_type": "Boat",
    "pathfinding_id": 1281875110,
    "movement_type": "Water",
    "can_enter_portals": false,
    "speed": [
      {
        "surface_type": "Ground",
        "speed": 0.0
      },
      {
        "surface_type": "Lake",
        "speed": 18.0
      },
      {
        "surface_type": "River",
        "speed": 18.0
      },
      {
        "surface_type": "Ocean",
        "speed": 22.0
      },
      {
        "surface_type": "OceanBiome",
        "speed": 25.0
      },
      {
        "surface_type": "Swamp",
        "speed": 18.0
      }
    ],
    "use_player_speed_modifier": false,
    "placeable_on_land": false,
    "placeable_in_water": true,
    "capacity": 4,
    "storage": 30,
    "stockpile": 6,
    "barter": 0,
    "item_slot_size": 6000,
    "cargo_slot_size": 60000,
    "model_address": "Vehicles/Clipper",
    "stats": [],
    "player_animations_in_deployable_slots": [
      1002,
      1002
    ],
    "allow_driver_extract": true,
    "allow_passenger_extract": true,
    "show_for_secs_after_owner_logout": 0,
    "allow_emote_while_driver": true,
    "allow_emote_while_passenger": true,
    "experience_per_progress": [
      {
        "skill_id": 21,
        "quantity": 0.0
      }
    ],
    "mounting_radius": 5.0
  },
  {
    "id": 571156212,
    "name": "Advanced Cart",
    "deploy_from_collectible_id": 1083393330,
    "deploy_time": 5.0,
    "deployable_type": "Cart",
    "pathfinding_id": 1375685503,
    "movement_type": "Ground",
    "can_enter_portals": true,
    "speed": [
      {
        "surface_type": "Ground",
        "speed": 15.0
      },
      {
        "surface_type": "Lake",
        "speed": 0.0
      },
      {
        "surface_type": "River",
        "speed": 0.0
      },
      {
        "surface_type": "Ocean",
        "speed": 0.0
      },
      {
        "surface_type": "OceanBiome",
        "speed": 0.0
      },
      {
        "surface_type": "Swamp",
        "speed": 0.0
      }
    ],
    "use_player_speed_modifier": true,
    "placeable_on_land": true,
    "placeable_in_water": false,
    "capacity": 1,
    "storage": 24,
    "stockpile": 3,
    "barter": 0,
    "item_slot_size": 6000,
    "cargo_slot_size": 60000,
    "model_address": "Vehicles/Cart",
    "stats": [],
    "player_animations_in_deployable_slots": [
      1
    ],
    "allow_driver_extract": false,
    "allow_passenger_extract": false,
    "show_for_secs_after_owner_logout": 0,
    "allow_emote_while_driver": false,
    "allow_emote_while_passenger": false,
    "experience_per_progress": [],
    "mounting_radius": 3.0
  },
  {
    "id": 634088959,
    "name": "Massive Personal Cache",
    "deploy_from_collectible_id": 693157662,
    "deploy_time": 3.0,
    "deployable_type": "Cache",
    "pathfinding_id": 1525146351,
    "movement_type": "None",
    "can_enter_portals": false,
    "speed": [
      {
        "surface_type": "Ground",
        "speed": 0.0
      },
      {
        "surface_type": "Lake",
        "speed": 0.0
      },
      {
        "surface_type": "River",
        "speed": 0.0
      },
      {
        "surface_type": "Ocean",
        "speed": 0.0
      },
      {
        "surface_type": "OceanBiome",
        "speed": 0.0
      },
      {
        "surface_type": "Swamp",
        "speed": 0.0
      }
    ],
    "use_player_speed_modifier": false,
    "placeable_on_land": true,
    "placeable_in_water": false,
    "capacity": 0,
    "storage": 72,
    "stockpile": 24,
    "barter": 0,
    "item_slot_size": 60000,
    "cargo_slot_size": 600000,
    "model_address": "Vehicles/PersonalCache",
    "stats": [],
    "player_animations_in_deployable_slots": [],
    "allow_driver_extract": false,
    "allow_passenger_extract": false,
    "show_for_secs_after_owner_logout": 0,
    "allow_emote_while_driver": false,
    "allow_emote_while_passenger": false,
    "experience_per_progress": [],
    "mounting_radius": 3.0
  },
  {
    "id": 872518914,
    "name": "Rideable Ox",
    "deploy_from_collectible_id": 1289105478,
    "deploy_time": 3.0,
    "deployable_type": "Mount",
    "pathfinding_id": 1301654297,
    "movement_type": "Ground",
    "can_enter_portals": true,
    "speed": [
      {
        "surface_type": "Ground",
        "speed": 18.0
      },
      {
        "surface_type": "Lake",
        "speed": 0.0
      },
      {
        "surface_type": "River",
        "speed": 0.0
      },
      {
        "surface_type": "Ocean",
        "speed": 0.0
      },
      {
        "surface_type": "OceanBiome",
        "speed": 0.0
      },
      {
        "surface_type": "Swamp",
        "speed": 0.0
      }
    ],
    "use_player_speed_modifier": false,
    "placeable_on_land": true,
    "placeable_in_water": false,
    "capacity": 2,
    "storage": 20,
    "stockpile": 6,
    "barter": 0,
    "item_slot_size": 60000,
    "cargo_slot_size": 18000,
    "model_address": "Vehicles/BisonMount",
    "stats": [],
    "player_animations_in_deployable_slots": [
      2,
      2
    ],
    "allow_driver_extract": false,
    "allow_passenger_extract": false,
    "show_for_secs_after_owner_logout": 0,
    "allow_emote_while_driver": false,
    "allow_emote_while_passenger": false,
    "experience_per_progress": [
      {
        "skill_id": 17,
        "quantity": 0.0
      }
    ],
    "mounting_radius": 3.0
  },
  {
    "id": 1026286338,
    "name": "Personal Cache",
    "deploy_from_collectible_id": 790337329,
    "deploy_time": 3.0,
    "deployable_type": "Cache",
    "pathfinding_id": 1525146351,
    "movement_type": "None",
    "can_enter_portals": false,
    "speed": [
      {
        "surface_type": "Ground",
        "speed": 0.0
      },
      {
        "surface_type": "Lake",
        "speed": 0.0
      },
      {
        "surface_type": "River",
        "speed": 0.0
      },
      {
        "surface_type": "Ocean",
        "speed": 0.0
      },
      {
        "surface_type": "OceanBiome",
        "speed": 0.0
      },
      {
        "surface_type": "Swamp",
        "speed": 0.0
      }
    ],
    "use_player_speed_modifier": false,
    "placeable_on_land": true,
    "placeable_in_water": false,
    "capacity": 0,
    "storage": 32,
    "stockpile": 8,
    "barter": 0,
    "item_slot_size": 60000,
    "cargo_slot_size": 600000,
    "model_address": "Vehicles/CrudePersonalCache",
    "stats": [],
    "player_animations_in_deployable_slots": [],
    "allow_driver_extract": false,
    "allow_passenger_extract": false,
    "show_for_secs_after_owner_logout": 0,
    "allow_emote_while_driver": false,
    "allow_emote_while_passenger": false,
    "experience_per_progress": [],
    "mounting_radius": 3.0
  },
  {
    "id": 1125730891,
    "name": "Rideable Goat",
    "deploy_from_collectible_id": 537052696,
    "deploy_time": 3.0,
    "deployable_type": "Mount",
    "pathfinding_id": 668511654,
    "movement_type": "Ground",
    "can_enter_portals": true,
    "speed": [
      {
        "surface_type": "Ground",
        "speed": 22.0
      },
      {
        "surface_type": "Lake",
        "speed": 0.0
      },
      {
        "surface_type": "River",
        "speed": 0.0
      },
      {
        "surface_type": "Ocean",
        "speed": 0.0
      },
      {
        "surface_type": "OceanBiome",
        "speed": 0.0
      },
      {
        "surface_type": "Swamp",
        "speed": 0.0
      }
    ],
    "use_player_speed_modifier": false,
    "placeable_on_land": true,
    "placeable_in_water": false,
    "capacity": 1,
    "storage": 0,
    "stockpile": 2,
    "barter": 0,
    "item_slot_size": 6000,
    "cargo_slot_size": 18000,
    "model_address": "Vehicles/GoatMount",
    "stats": [],
    "player_animations_in_deployable_slots": [
      2
    ],
    "allow_driver_extract": false,
    "allow_passenger_extract": false,
    "show_for_secs_after_owner_logout": 0,
    "allow_emote_while_driver": false,
    "allow_emote_while_passenger": false,
    "experience_per_progress": [
      {
        "skill_id": 17,
        "quantity": 0.0
      }
    ],
    "mounting_radius": 3.0
  },
  {
    "id": 1338380321,
    "name": "Rideable Bird",
    "deploy_from_collectible_id": 1163358546,
    "deploy_time": 3.0,
    "deployable_type": "Mount",
    "pathfinding_id": 1301654297,
    "movement_type": "Ground",
    "can_enter_portals": true,
    "speed": [
      {
        "surface_type": "Ground",
        "speed": 31.0
      },
      {
        "surface_type": "Lake",
        "speed": 0.0
      },
      {
        "surface_type": "River",
        "speed": 0.0
      },
      {
        "surface_type": "Ocean",
        "speed": 0.0
      },
      {
        "surface_type": "OceanBiome",
        "speed": 0.0
      },
      {
        "surface_type": "Swamp",
        "speed": 0.0
      }
    ],
    "use_player_speed_modifier": false,
    "placeable_on_land": true,
    "placeable_in_water": false,
    "capacity": 1,
    "storage": 0,
    "stockpile": 0,
    "barter": 0,
    "item_slot_size": 6000,
    "cargo_slot_size": 6000,
    "model_address": "Vehicles/TerrorbirdMount",
    "stats": [],
    "player_animations_in_deployable_slots": [
      2
    ],
    "allow_driver_extract": false,
    "allow_passenger_extract": false,
    "show_for_secs_after_owner_logout": 0,
    "allow_emote_while_driver": false,
    "allow_emote_while_passenger": false,
    "experience_per_progress": [
      {
        "skill_id": 17,
        "quantity": 0.0
      }
    ],
    "mounting_radius": 3.0
  },
  {
    "id": 1357146109,
    "name": "Cargo Ship",
    "deploy_from_collectible_id": 700235689,
    "deploy_time": 5.0,
    "deployable_type": "Boat",
    "pathfinding_id": 1876455160,
    "movement_type": "Water",
    "can_enter_portals": false,
    "speed": [
      {
        "surface_type": "Ground",
        "speed": 0.0
      },
      {
        "surface_type": "Lake",
        "speed": 15.0
      },
      {
        "surface_type": "River",
        "speed": 15.0
      },
      {
        "surface_type": "Ocean",
        "speed": 21.0
      },
      {
        "surface_type": "OceanBiome",
        "speed": 21.0
      },
      {
        "surface_type": "Swamp",
        "speed": 15.0
      }
    ],
    "use_player_speed_modifier": false,
    "placeable_on_land": false,
    "placeable_in_water": true,
    "capacity": 6,
    "storage": 30,
    "stockpile": 10,
    "barter": 0,
    "item_slot_size": 6000,
    "cargo_slot_size": 60000,
    "model_address": "Vehicles/CargoShip",
    "stats": [],
    "player_animations_in_deployable_slots": [
      1002,
      1002
    ],
    "allow_driver_extract": true,
    "allow_passenger_extract": true,
    "show_for_secs_after_owner_logout": 0,
    "allow_emote_while_driver": true,
    "allow_emote_while_passenger": true,
    "experience_per_progress": [
      {
        "skill_id": 21,
        "quantity": 0.0
      }
    ],
    "mounting_radius": 5.0
  },
  {
    "id": 1554573049,
    "name": "Improved Wagon",
    "deploy_from_collectible_id": 1520209370,
    "deploy_time": 5.0,
    "deployable_type": "Cart",
    "pathfinding_id": 1030168975,
    "movement_type": "Ground",
    "can_enter_portals": true,
    "speed": [
      {
        "surface_type": "Ground",
        "speed": 11.0
      },
      {
        "surface_type": "Lake",
        "speed": 0.0
      },
      {
        "surface_type": "River",
        "speed": 0.0
      },
      {
        "surface_type": "Ocean",
        "speed": 0.0
      },
      {
        "surface_type": "OceanBiome",
        "speed": 0.0
      },
      {
        "surface_type": "Swamp",
        "speed": 0.0
      }
    ],
    "use_player_speed_modifier": true,
    "placeable_on_land": true,
    "placeable_in_water": false,
    "capacity": 1,
    "storage": 16,
    "stockpile": 8,
    "barter": 0,
    "item_slot_size": 6000,
    "cargo_slot_size": 60000,
    "model_address": "Vehicles/LargeCart",
    "stats": [],
    "player_animations_in_deployable_slots": [
      1
    ],
    "allow_driver_extract": false,
    "allow_passenger_extract": false,
    "show_for_secs_after_owner_logout": 0,
    "allow_emote_while_driver": false,
    "allow_emote_while_passenger": false,
    "experience_per_progress": [],
    "mounting_radius": 3.0
  },
  {
    "id": 1596080513,
    "name": "Improved Cart",
    "deploy_from_collectible_id": 684496199,
    "deploy_time": 5.0,
    "deployable_type": "Cart",
    "pathfinding_id": 1375685503,
    "movement_type": "Ground",
    "can_enter_portals": true,
    "speed": [
      {
        "surface_type": "Ground",
        "speed": 14.0
      },
      {
        "surface_type": "Lake",
        "speed": 0.0
      },
      {
        "surface_type": "River",
        "speed": 0.0
      },
      {
        "surface_type": "Ocean",
        "speed": 0.0
      },
      {
        "surface_type": "OceanBiome",
        "speed": 0.0
      },
      {
        "surface_type": "Swamp",
        "speed": 0.0
      }
    ],
    "use_player_speed_modifier": true,
    "placeable_on_land": true,
    "placeable_in_water": false,
    "capacity": 1,
    "storage": 18,
    "stockpile": 2,
    "barter": 0,
    "item_slot_size": 6000,
    "cargo_slot_size": 60000,
    "model_address": "Vehicles/Cart",
    "stats": [],
    "player_animations_in_deployable_slots": [
      1
    ],
    "allow_driver_extract": false,
    "allow_passenger_extract": false,
    "show_for_secs_after_owner_logout": 0,
    "allow_emote_while_driver": false,
    "allow_emote_while_passenger": false,
    "experience_per_progress": [],
    "mounting_radius": 3.0
  },
  {
    "id": 1641732157,
    "name": "Expanded Personal Cache",
    "deploy_from_collectible_id": 1226450761,
    "deploy_time": 3.0,
    "deployable_type": "Cache",
    "pathfinding_id": 1525146351,
    "movement_type": "None",
    "can_enter_portals": false,
    "speed": [
      {
        "surface_type": "Ground",
        "speed": 0.0
      },
      {
        "surface_type": "Lake",
        "speed": 0.0
      },
      {
        "surface_type": "River",
        "speed": 0.0
      },
      {
        "surface_type": "Ocean",
        "speed": 0.0
      },
      {
        "surface_type": "OceanBiome",
        "speed": 0.0
      },
      {
        "surface_type": "Swamp",
        "speed": 0.0
      }
    ],
    "use_player_speed_modifier": false,
    "placeable_on_land": true,
    "placeable_in_water": false,
    "capacity": 0,
    "storage": 48,
    "stockpile": 16,
    "barter": 0,
    "item_slot_size": 60000,
    "cargo_slot_size": 600000,
    "model_address": "Vehicles/PersonalCache",
    "stats": [],
    "player_animations_in_deployable_slots": [],
    "allow_driver_extract": false,
    "allow_passenger_extract": false,
    "show_for_secs_after_owner_logout": 0,
    "allow_emote_while_driver": false,
    "allow_emote_while_passenger": false,
    "experience_per_progress": [],
    "mounting_radius": 3.0
  },
  {
    "id": 2045051661,
    "name": "Advanced Wagon",
    "deploy_from_collectible_id": 381044074,
    "deploy_time": 5.0,
    "deployable_type": "Cart",
    "pathfinding_id": 1030168975,
    "movement_type": "Ground",
    "can_enter_portals": true,
    "speed": [
      {
        "surface_type": "Ground",
        "speed": 12.0
      },
      {
        "surface_type": "Lake",
        "speed": 0.0
      },
      {
        "surface_type": "River",
        "speed": 0.0
      },
      {
        "surface_type": "Ocean",
        "speed": 0.0
      },
      {
        "surface_type": "OceanBiome",
        "speed": 0.0
      },
      {
        "surface_type": "Swamp",
        "speed": 0.0
      }
    ],
    "use_player_speed_modifier": true,
    "placeable_on_land": true,
    "placeable_in_water": false,
    "capacity": 1,
    "storage": 20,
    "stockpile": 10,
    "barter": 0,
    "item_slot_size": 6000,
    "cargo_slot_size": 60000,
    "model_address": "Vehicles/LargeCart",
    "stats": [],
    "player_animations_in_deployable_slots": [
      1
    ],
    "allow_driver_extract": false,
    "allow_passenger_extract": false,
    "show_for_secs_after_owner_logout": 0,
    "allow_emote_while_driver": false,
    "allow_emote_while_passenger": false,
    "experience_per_progress": [],
    "mounting_radius": 3.0
  },
  {
    "id": 2065423994,
    "name": "Rickshaw Cart",
    "deploy_from_collectible_id": 1586159687,
    "deploy_time": 5.0,
    "deployable_type": "Cart",
    "pathfinding_id": 1375685503,
    "movement_type": "Ground",
    "can_enter_portals": true,
    "speed": [
      {
        "surface_type": "Ground",
        "speed": 18.0
      },
      {
        "surface_type": "Lake",
        "speed": 0.0
      },
      {
        "surface_type": "River",
        "speed": 0.0
      },
      {
        "surface_type": "Ocean",
        "speed": 0.0
      },
      {
        "surface_type": "OceanBiome",
        "speed": 0.0
      },
      {
        "surface_type": "Swamp",
        "speed": 0.0
      }
    ],
    "use_player_speed_modifier": true,
    "placeable_on_land": true,
    "placeable_in_water": false,
    "capacity": 2,
    "storage": 12,
    "stockpile": 0,
    "barter": 0,
    "item_slot_size": 6000,
    "cargo_slot_size": 60000,
    "model_address": "Vehicles/Rickshaw",
    "stats": [],
    "player_animations_in_deployable_slots": [
      1,
      1000
    ],
    "allow_driver_extract": false,
    "allow_passenger_extract": false,
    "show_for_secs_after_owner_logout": 0,
    "allow_emote_while_driver": false,
    "allow_emote_while_passenger": false,
    "experience_per_progress": [],
    "mounting_radius": 3.0
  }
]