[
  {
    "id": 229709100,
    "name": "AlesiHideout",
    "skybox_material": "Interiors_Sky",
    "realtime_shadow_color": 4285233824,
    "lighting_source": 3,
    "lighting_skybox_intensity": 0.6,
    "lighting_gradient_sky_color": 4285233817,
    "lighting_gradient_equator_color": 4280098850,
    "lighting_gradient_ground_color": 4278979337,
    "lighting_color_ambient_color": 4285233817,
    "fog_enable": false,
    "fog_color": 4289850363,
    "fog_mode": 3,
    "fog_density": 0.0025,
    "fog_start_distance": 0.0,
    "fog_end_distance": 300.0
  },
  {
    "id": 1802146406,
    "name": "Tower",
    "skybox_material": "Interiors_Sky",
    "realtime_shadow_color": 4285233824,
    "lighting_source": 3,
    "lighting_skybox_intensity": 0.6,
    "lighting_gradient_sky_color": 4285233817,
    "lighting_gradient_equator_color": 4280098850,
    "lighting_gradient_ground_color": 4278979337,
    "lighting_color_ambient_color": 4282409088,
    "fog_enable": false,
    "fog_color": 4289850363,
    "fog_mode": 3,
    "fog_density": 0.0025,
    "fog_start_distance": 0.0,
    "fog_end_distance": 300.0
  }
]